{
    "area_cleared_m2": "area_cleared_m2",
    "completion_time": "completion_time",
    "description": "description",
    "from_fms": "from_fms",
    "geometry": "geometry",
    "import_date": "import_date",
    "import_datetime": "import_datetime",
    "import_day": "import_day",
    "import_month": "import_month",
    "import_timestamp": "import_timestamp",
    "import_year": "import_year",
    "incident_job_type": "incident_job_type",
    "item_id": "item_id",
    "root_incident_job_type_incident_job_type_incident_job_type": "job_type",
    "root_incident_job_type_incident_job_type_item_ids": "job_type_id",
    "nearest_address": "nearest_address",
    "offensive": "offensive",
    "raised_time": "raised_time",
    "refined_date": "refined_date",
    "refined_day": "refined_day",
    "refined_month": "refined_month",
    "refined_year": "refined_year",
    "start_time": "start_time",
    "root_status_task_statuses_status": "status",
    "status": "status_id",
    "root_status_task_statuses_item_ids": "status_id_1",
    "subtitle": "subtitle",
    "root_team_teams_team_name": "team_name",
    "root_team_teams_item_ids": "team_name_id",
    "title": "title"
}